[
    {
     "id":"bar001",
     "type": "bar",
     "size": "44",
     "description":"This is a test vote",
     "options":[
        {"option":"Red","name":"bar001"},
        {"option":"Blue","name":"bar001"},
        {"option":"Yellow","name":"bar001"},
        {"option":"Green","name":"bar001"},
        {"option":"Purple","name":"bar001"},
        {"option":"Orange","name":"bar001"} 
     ],
     "photoURL":"https://encrypted-tbn0.gstatic.com/images?q=tbn:ANd9GcRc1gsfb8QynQR8mmEBXimRBtUYu1mBzWCJORiMs4dfLmOc4WYw",
     "chartData":{
        "type": "bar",
        "data": {
            "labels": ["Red", "Blue", "Yellow", "Green", "Purple", "Orange"],
            "datasets": [{
                "label": "# of Votes",
                "data": [12, 19, 3, 5, 2, 3],
                "backgroundColor": [
                    "rgba(255, 99, 132, 0.2)",
                    "rgba(54, 162, 235, 0.2)",
                    "rgba(255, 206, 86, 0.2)",
                    "rgba(75, 192, 192, 0.2)",
                    "rgba(153, 102, 255, 0.2)",
                    "rgba(255, 159, 64, 0.2)"
                ],
                "borderColor": [
                    "rgba(255,99,132,1)",
                    "rgba(54, 162, 235, 1)",
                    "rgba(255, 206, 86, 1)",
                    "rgba(75, 192, 192, 1)",
                    "rgba(153, 102, 255, 1)",
                    "rgba(255, 159, 64, 1)"
                ],
                "borderWidth": 1
            }]
        },
        "options": {"scales": {"yAxes": [{"ticks":{"beginAtZero":true}}]}}
    }
    }
]